{"dependencies":[{"name":"/home/kyle/Documents/league-for-good/package.json","includedInParent":true,"mtime":1521424227786},{"name":"/home/kyle/Documents/league-for-good/.babelrc","includedInParent":true,"mtime":1513548591197},{"name":"/home/kyle/Documents/league-for-good/node_modules/react-dom/package.json","includedInParent":true,"mtime":1513548629049},{"name":"./ReactDOMComponentTree","loc":{"line":11,"column":36}}],"generated":{"js":"/**\n * Copyright (c) 2013-present, Facebook, Inc.\n *\n * This source code is licensed under the MIT license found in the\n * LICENSE file in the root directory of this source tree.\n *\n */\n\n'use strict';\n\nvar ReactDOMComponentTree = require('./ReactDOMComponentTree');\n\nfunction isCheckable(elem) {\n  var type = elem.type;\n  var nodeName = elem.nodeName;\n  return nodeName && nodeName.toLowerCase() === 'input' && (type === 'checkbox' || type === 'radio');\n}\n\nfunction getTracker(inst) {\n  return inst._wrapperState.valueTracker;\n}\n\nfunction attachTracker(inst, tracker) {\n  inst._wrapperState.valueTracker = tracker;\n}\n\nfunction detachTracker(inst) {\n  inst._wrapperState.valueTracker = null;\n}\n\nfunction getValueFromNode(node) {\n  var value;\n  if (node) {\n    value = isCheckable(node) ? '' + node.checked : node.value;\n  }\n  return value;\n}\n\nvar inputValueTracking = {\n  // exposed for testing\n  _getTrackerFromNode: function (node) {\n    return getTracker(ReactDOMComponentTree.getInstanceFromNode(node));\n  },\n\n\n  track: function (inst) {\n    if (getTracker(inst)) {\n      return;\n    }\n\n    var node = ReactDOMComponentTree.getNodeFromInstance(inst);\n    var valueField = isCheckable(node) ? 'checked' : 'value';\n    var descriptor = Object.getOwnPropertyDescriptor(node.constructor.prototype, valueField);\n\n    var currentValue = '' + node[valueField];\n\n    // if someone has already defined a value or Safari, then bail\n    // and don't track value will cause over reporting of changes,\n    // but it's better then a hard failure\n    // (needed for certain tests that spyOn input values and Safari)\n    if (node.hasOwnProperty(valueField) || typeof descriptor.get !== 'function' || typeof descriptor.set !== 'function') {\n      return;\n    }\n\n    Object.defineProperty(node, valueField, {\n      enumerable: descriptor.enumerable,\n      configurable: true,\n      get: function () {\n        return descriptor.get.call(this);\n      },\n      set: function (value) {\n        currentValue = '' + value;\n        descriptor.set.call(this, value);\n      }\n    });\n\n    attachTracker(inst, {\n      getValue: function () {\n        return currentValue;\n      },\n      setValue: function (value) {\n        currentValue = '' + value;\n      },\n      stopTracking: function () {\n        detachTracker(inst);\n        delete node[valueField];\n      }\n    });\n  },\n\n  updateValueIfChanged: function (inst) {\n    if (!inst) {\n      return false;\n    }\n    var tracker = getTracker(inst);\n\n    if (!tracker) {\n      inputValueTracking.track(inst);\n      return true;\n    }\n\n    var lastValue = tracker.getValue();\n    var nextValue = getValueFromNode(ReactDOMComponentTree.getNodeFromInstance(inst));\n\n    if (nextValue !== lastValue) {\n      tracker.setValue(nextValue);\n      return true;\n    }\n\n    return false;\n  },\n  stopTracking: function (inst) {\n    var tracker = getTracker(inst);\n    if (tracker) {\n      tracker.stopTracking();\n    }\n  }\n};\n\nmodule.exports = inputValueTracking;","map":{"mappings":[{"source":"../node_modules/react-dom/lib/inputValueTracking.js","original":{"line":1,"column":0},"generated":{"line":1,"column":0}},{"source":"../node_modules/react-dom/lib/inputValueTracking.js","original":{"line":2,"column":0},"generated":{"line":2,"column":0}},{"source":"../node_modules/react-dom/lib/inputValueTracking.js","original":{"line":3,"column":0},"generated":{"line":3,"column":0}},{"source":"../node_modules/react-dom/lib/inputValueTracking.js","original":{"line":4,"column":0},"generated":{"line":4,"column":0}},{"source":"../node_modules/react-dom/lib/inputValueTracking.js","original":{"line":5,"column":0},"generated":{"line":5,"column":0}},{"source":"../node_modules/react-dom/lib/inputValueTracking.js","original":{"line":6,"column":0},"generated":{"line":6,"column":0}},{"source":"../node_modules/react-dom/lib/inputValueTracking.js","original":{"line":7,"column":0},"generated":{"line":7,"column":0}},{"source":"../node_modules/react-dom/lib/inputValueTracking.js","original":{"line":8,"column":0},"generated":{"line":8,"column":0}},{"source":"../node_modules/react-dom/lib/inputValueTracking.js","original":{"line":9,"column":0},"generated":{"line":9,"column":0}},{"source":"../node_modules/react-dom/lib/inputValueTracking.js","original":{"line":10,"column":0},"generated":{"line":10,"column":0}},{"source":"../node_modules/react-dom/lib/inputValueTracking.js","original":{"line":11,"column":0},"generated":{"line":11,"column":0}},{"source":"../node_modules/react-dom/lib/inputValueTracking.js","original":{"line":12,"column":0},"generated":{"line":12,"column":0}},{"source":"../node_modules/react-dom/lib/inputValueTracking.js","original":{"line":13,"column":0},"generated":{"line":13,"column":0}},{"source":"../node_modules/react-dom/lib/inputValueTracking.js","original":{"line":14,"column":0},"generated":{"line":14,"column":0}},{"source":"../node_modules/react-dom/lib/inputValueTracking.js","original":{"line":15,"column":0},"generated":{"line":15,"column":0}},{"source":"../node_modules/react-dom/lib/inputValueTracking.js","original":{"line":16,"column":0},"generated":{"line":16,"column":0}},{"source":"../node_modules/react-dom/lib/inputValueTracking.js","original":{"line":17,"column":0},"generated":{"line":17,"column":0}},{"source":"../node_modules/react-dom/lib/inputValueTracking.js","original":{"line":18,"column":0},"generated":{"line":18,"column":0}},{"source":"../node_modules/react-dom/lib/inputValueTracking.js","original":{"line":19,"column":0},"generated":{"line":19,"column":0}},{"source":"../node_modules/react-dom/lib/inputValueTracking.js","original":{"line":20,"column":0},"generated":{"line":20,"column":0}},{"source":"../node_modules/react-dom/lib/inputValueTracking.js","original":{"line":21,"column":0},"generated":{"line":21,"column":0}},{"source":"../node_modules/react-dom/lib/inputValueTracking.js","original":{"line":22,"column":0},"generated":{"line":22,"column":0}},{"source":"../node_modules/react-dom/lib/inputValueTracking.js","original":{"line":23,"column":0},"generated":{"line":23,"column":0}},{"source":"../node_modules/react-dom/lib/inputValueTracking.js","original":{"line":24,"column":0},"generated":{"line":24,"column":0}},{"source":"../node_modules/react-dom/lib/inputValueTracking.js","original":{"line":25,"column":0},"generated":{"line":25,"column":0}},{"source":"../node_modules/react-dom/lib/inputValueTracking.js","original":{"line":26,"column":0},"generated":{"line":26,"column":0}},{"source":"../node_modules/react-dom/lib/inputValueTracking.js","original":{"line":27,"column":0},"generated":{"line":27,"column":0}},{"source":"../node_modules/react-dom/lib/inputValueTracking.js","original":{"line":28,"column":0},"generated":{"line":28,"column":0}},{"source":"../node_modules/react-dom/lib/inputValueTracking.js","original":{"line":29,"column":0},"generated":{"line":29,"column":0}},{"source":"../node_modules/react-dom/lib/inputValueTracking.js","original":{"line":30,"column":0},"generated":{"line":30,"column":0}},{"source":"../node_modules/react-dom/lib/inputValueTracking.js","original":{"line":31,"column":0},"generated":{"line":31,"column":0}},{"source":"../node_modules/react-dom/lib/inputValueTracking.js","original":{"line":32,"column":0},"generated":{"line":32,"column":0}},{"source":"../node_modules/react-dom/lib/inputValueTracking.js","original":{"line":33,"column":0},"generated":{"line":33,"column":0}},{"source":"../node_modules/react-dom/lib/inputValueTracking.js","original":{"line":34,"column":0},"generated":{"line":34,"column":0}},{"source":"../node_modules/react-dom/lib/inputValueTracking.js","original":{"line":35,"column":0},"generated":{"line":35,"column":0}},{"source":"../node_modules/react-dom/lib/inputValueTracking.js","original":{"line":36,"column":0},"generated":{"line":36,"column":0}},{"source":"../node_modules/react-dom/lib/inputValueTracking.js","original":{"line":37,"column":0},"generated":{"line":37,"column":0}},{"source":"../node_modules/react-dom/lib/inputValueTracking.js","original":{"line":38,"column":0},"generated":{"line":38,"column":0}},{"source":"../node_modules/react-dom/lib/inputValueTracking.js","original":{"line":39,"column":0},"generated":{"line":39,"column":0}},{"source":"../node_modules/react-dom/lib/inputValueTracking.js","original":{"line":40,"column":0},"generated":{"line":40,"column":0}},{"source":"../node_modules/react-dom/lib/inputValueTracking.js","original":{"line":41,"column":0},"generated":{"line":41,"column":0}},{"source":"../node_modules/react-dom/lib/inputValueTracking.js","original":{"line":42,"column":0},"generated":{"line":42,"column":0}},{"source":"../node_modules/react-dom/lib/inputValueTracking.js","original":{"line":43,"column":0},"generated":{"line":43,"column":0}},{"source":"../node_modules/react-dom/lib/inputValueTracking.js","original":{"line":44,"column":0},"generated":{"line":44,"column":0}},{"source":"../node_modules/react-dom/lib/inputValueTracking.js","original":{"line":45,"column":0},"generated":{"line":45,"column":0}},{"source":"../node_modules/react-dom/lib/inputValueTracking.js","original":{"line":46,"column":0},"generated":{"line":46,"column":0}},{"source":"../node_modules/react-dom/lib/inputValueTracking.js","original":{"line":47,"column":0},"generated":{"line":47,"column":0}},{"source":"../node_modules/react-dom/lib/inputValueTracking.js","original":{"line":48,"column":0},"generated":{"line":48,"column":0}},{"source":"../node_modules/react-dom/lib/inputValueTracking.js","original":{"line":49,"column":0},"generated":{"line":49,"column":0}},{"source":"../node_modules/react-dom/lib/inputValueTracking.js","original":{"line":50,"column":0},"generated":{"line":50,"column":0}},{"source":"../node_modules/react-dom/lib/inputValueTracking.js","original":{"line":51,"column":0},"generated":{"line":51,"column":0}},{"source":"../node_modules/react-dom/lib/inputValueTracking.js","original":{"line":52,"column":0},"generated":{"line":52,"column":0}},{"source":"../node_modules/react-dom/lib/inputValueTracking.js","original":{"line":53,"column":0},"generated":{"line":53,"column":0}},{"source":"../node_modules/react-dom/lib/inputValueTracking.js","original":{"line":54,"column":0},"generated":{"line":54,"column":0}},{"source":"../node_modules/react-dom/lib/inputValueTracking.js","original":{"line":55,"column":0},"generated":{"line":55,"column":0}},{"source":"../node_modules/react-dom/lib/inputValueTracking.js","original":{"line":56,"column":0},"generated":{"line":56,"column":0}},{"source":"../node_modules/react-dom/lib/inputValueTracking.js","original":{"line":57,"column":0},"generated":{"line":57,"column":0}},{"source":"../node_modules/react-dom/lib/inputValueTracking.js","original":{"line":58,"column":0},"generated":{"line":58,"column":0}},{"source":"../node_modules/react-dom/lib/inputValueTracking.js","original":{"line":59,"column":0},"generated":{"line":59,"column":0}},{"source":"../node_modules/react-dom/lib/inputValueTracking.js","original":{"line":60,"column":0},"generated":{"line":60,"column":0}},{"source":"../node_modules/react-dom/lib/inputValueTracking.js","original":{"line":61,"column":0},"generated":{"line":61,"column":0}},{"source":"../node_modules/react-dom/lib/inputValueTracking.js","original":{"line":62,"column":0},"generated":{"line":62,"column":0}},{"source":"../node_modules/react-dom/lib/inputValueTracking.js","original":{"line":63,"column":0},"generated":{"line":63,"column":0}},{"source":"../node_modules/react-dom/lib/inputValueTracking.js","original":{"line":64,"column":0},"generated":{"line":64,"column":0}},{"source":"../node_modules/react-dom/lib/inputValueTracking.js","original":{"line":65,"column":0},"generated":{"line":65,"column":0}},{"source":"../node_modules/react-dom/lib/inputValueTracking.js","original":{"line":66,"column":0},"generated":{"line":66,"column":0}},{"source":"../node_modules/react-dom/lib/inputValueTracking.js","original":{"line":67,"column":0},"generated":{"line":67,"column":0}},{"source":"../node_modules/react-dom/lib/inputValueTracking.js","original":{"line":68,"column":0},"generated":{"line":68,"column":0}},{"source":"../node_modules/react-dom/lib/inputValueTracking.js","original":{"line":69,"column":0},"generated":{"line":69,"column":0}},{"source":"../node_modules/react-dom/lib/inputValueTracking.js","original":{"line":70,"column":0},"generated":{"line":70,"column":0}},{"source":"../node_modules/react-dom/lib/inputValueTracking.js","original":{"line":71,"column":0},"generated":{"line":71,"column":0}},{"source":"../node_modules/react-dom/lib/inputValueTracking.js","original":{"line":72,"column":0},"generated":{"line":72,"column":0}},{"source":"../node_modules/react-dom/lib/inputValueTracking.js","original":{"line":73,"column":0},"generated":{"line":73,"column":0}},{"source":"../node_modules/react-dom/lib/inputValueTracking.js","original":{"line":74,"column":0},"generated":{"line":74,"column":0}},{"source":"../node_modules/react-dom/lib/inputValueTracking.js","original":{"line":75,"column":0},"generated":{"line":75,"column":0}},{"source":"../node_modules/react-dom/lib/inputValueTracking.js","original":{"line":76,"column":0},"generated":{"line":76,"column":0}},{"source":"../node_modules/react-dom/lib/inputValueTracking.js","original":{"line":77,"column":0},"generated":{"line":77,"column":0}},{"source":"../node_modules/react-dom/lib/inputValueTracking.js","original":{"line":78,"column":0},"generated":{"line":78,"column":0}},{"source":"../node_modules/react-dom/lib/inputValueTracking.js","original":{"line":79,"column":0},"generated":{"line":79,"column":0}},{"source":"../node_modules/react-dom/lib/inputValueTracking.js","original":{"line":80,"column":0},"generated":{"line":80,"column":0}},{"source":"../node_modules/react-dom/lib/inputValueTracking.js","original":{"line":81,"column":0},"generated":{"line":81,"column":0}},{"source":"../node_modules/react-dom/lib/inputValueTracking.js","original":{"line":82,"column":0},"generated":{"line":82,"column":0}},{"source":"../node_modules/react-dom/lib/inputValueTracking.js","original":{"line":83,"column":0},"generated":{"line":83,"column":0}},{"source":"../node_modules/react-dom/lib/inputValueTracking.js","original":{"line":84,"column":0},"generated":{"line":84,"column":0}},{"source":"../node_modules/react-dom/lib/inputValueTracking.js","original":{"line":85,"column":0},"generated":{"line":85,"column":0}},{"source":"../node_modules/react-dom/lib/inputValueTracking.js","original":{"line":86,"column":0},"generated":{"line":86,"column":0}},{"source":"../node_modules/react-dom/lib/inputValueTracking.js","original":{"line":87,"column":0},"generated":{"line":87,"column":0}},{"source":"../node_modules/react-dom/lib/inputValueTracking.js","original":{"line":88,"column":0},"generated":{"line":88,"column":0}},{"source":"../node_modules/react-dom/lib/inputValueTracking.js","original":{"line":89,"column":0},"generated":{"line":89,"column":0}},{"source":"../node_modules/react-dom/lib/inputValueTracking.js","original":{"line":90,"column":0},"generated":{"line":90,"column":0}},{"source":"../node_modules/react-dom/lib/inputValueTracking.js","original":{"line":91,"column":0},"generated":{"line":91,"column":0}},{"source":"../node_modules/react-dom/lib/inputValueTracking.js","original":{"line":92,"column":0},"generated":{"line":92,"column":0}},{"source":"../node_modules/react-dom/lib/inputValueTracking.js","original":{"line":93,"column":0},"generated":{"line":93,"column":0}},{"source":"../node_modules/react-dom/lib/inputValueTracking.js","original":{"line":94,"column":0},"generated":{"line":94,"column":0}},{"source":"../node_modules/react-dom/lib/inputValueTracking.js","original":{"line":95,"column":0},"generated":{"line":95,"column":0}},{"source":"../node_modules/react-dom/lib/inputValueTracking.js","original":{"line":96,"column":0},"generated":{"line":96,"column":0}},{"source":"../node_modules/react-dom/lib/inputValueTracking.js","original":{"line":97,"column":0},"generated":{"line":97,"column":0}},{"source":"../node_modules/react-dom/lib/inputValueTracking.js","original":{"line":98,"column":0},"generated":{"line":98,"column":0}},{"source":"../node_modules/react-dom/lib/inputValueTracking.js","original":{"line":99,"column":0},"generated":{"line":99,"column":0}},{"source":"../node_modules/react-dom/lib/inputValueTracking.js","original":{"line":100,"column":0},"generated":{"line":100,"column":0}},{"source":"../node_modules/react-dom/lib/inputValueTracking.js","original":{"line":101,"column":0},"generated":{"line":101,"column":0}},{"source":"../node_modules/react-dom/lib/inputValueTracking.js","original":{"line":102,"column":0},"generated":{"line":102,"column":0}},{"source":"../node_modules/react-dom/lib/inputValueTracking.js","original":{"line":103,"column":0},"generated":{"line":103,"column":0}},{"source":"../node_modules/react-dom/lib/inputValueTracking.js","original":{"line":104,"column":0},"generated":{"line":104,"column":0}},{"source":"../node_modules/react-dom/lib/inputValueTracking.js","original":{"line":105,"column":0},"generated":{"line":105,"column":0}},{"source":"../node_modules/react-dom/lib/inputValueTracking.js","original":{"line":106,"column":0},"generated":{"line":106,"column":0}},{"source":"../node_modules/react-dom/lib/inputValueTracking.js","original":{"line":107,"column":0},"generated":{"line":107,"column":0}},{"source":"../node_modules/react-dom/lib/inputValueTracking.js","original":{"line":108,"column":0},"generated":{"line":108,"column":0}},{"source":"../node_modules/react-dom/lib/inputValueTracking.js","original":{"line":109,"column":0},"generated":{"line":109,"column":0}},{"source":"../node_modules/react-dom/lib/inputValueTracking.js","original":{"line":110,"column":0},"generated":{"line":110,"column":0}},{"source":"../node_modules/react-dom/lib/inputValueTracking.js","original":{"line":111,"column":0},"generated":{"line":111,"column":0}},{"source":"../node_modules/react-dom/lib/inputValueTracking.js","original":{"line":112,"column":0},"generated":{"line":112,"column":0}},{"source":"../node_modules/react-dom/lib/inputValueTracking.js","original":{"line":113,"column":0},"generated":{"line":113,"column":0}},{"source":"../node_modules/react-dom/lib/inputValueTracking.js","original":{"line":114,"column":0},"generated":{"line":114,"column":0}},{"source":"../node_modules/react-dom/lib/inputValueTracking.js","original":{"line":115,"column":0},"generated":{"line":115,"column":0}},{"source":"../node_modules/react-dom/lib/inputValueTracking.js","original":{"line":116,"column":0},"generated":{"line":116,"column":0}},{"source":"../node_modules/react-dom/lib/inputValueTracking.js","original":{"line":117,"column":0},"generated":{"line":117,"column":0}},{"source":"../node_modules/react-dom/lib/inputValueTracking.js","original":{"line":118,"column":0},"generated":{"line":118,"column":0}},{"source":"../node_modules/react-dom/lib/inputValueTracking.js","original":{"line":119,"column":0},"generated":{"line":119,"column":0}},{"source":"../node_modules/react-dom/lib/inputValueTracking.js","original":{"line":120,"column":0},"generated":{"line":120,"column":0}}],"sources":{"../node_modules/react-dom/lib/inputValueTracking.js":"/**\n * Copyright (c) 2013-present, Facebook, Inc.\n *\n * This source code is licensed under the MIT license found in the\n * LICENSE file in the root directory of this source tree.\n *\n */\n\n'use strict';\n\nvar ReactDOMComponentTree = require('./ReactDOMComponentTree');\n\nfunction isCheckable(elem) {\n  var type = elem.type;\n  var nodeName = elem.nodeName;\n  return nodeName && nodeName.toLowerCase() === 'input' && (type === 'checkbox' || type === 'radio');\n}\n\nfunction getTracker(inst) {\n  return inst._wrapperState.valueTracker;\n}\n\nfunction attachTracker(inst, tracker) {\n  inst._wrapperState.valueTracker = tracker;\n}\n\nfunction detachTracker(inst) {\n  inst._wrapperState.valueTracker = null;\n}\n\nfunction getValueFromNode(node) {\n  var value;\n  if (node) {\n    value = isCheckable(node) ? '' + node.checked : node.value;\n  }\n  return value;\n}\n\nvar inputValueTracking = {\n  // exposed for testing\n  _getTrackerFromNode: function (node) {\n    return getTracker(ReactDOMComponentTree.getInstanceFromNode(node));\n  },\n\n\n  track: function (inst) {\n    if (getTracker(inst)) {\n      return;\n    }\n\n    var node = ReactDOMComponentTree.getNodeFromInstance(inst);\n    var valueField = isCheckable(node) ? 'checked' : 'value';\n    var descriptor = Object.getOwnPropertyDescriptor(node.constructor.prototype, valueField);\n\n    var currentValue = '' + node[valueField];\n\n    // if someone has already defined a value or Safari, then bail\n    // and don't track value will cause over reporting of changes,\n    // but it's better then a hard failure\n    // (needed for certain tests that spyOn input values and Safari)\n    if (node.hasOwnProperty(valueField) || typeof descriptor.get !== 'function' || typeof descriptor.set !== 'function') {\n      return;\n    }\n\n    Object.defineProperty(node, valueField, {\n      enumerable: descriptor.enumerable,\n      configurable: true,\n      get: function () {\n        return descriptor.get.call(this);\n      },\n      set: function (value) {\n        currentValue = '' + value;\n        descriptor.set.call(this, value);\n      }\n    });\n\n    attachTracker(inst, {\n      getValue: function () {\n        return currentValue;\n      },\n      setValue: function (value) {\n        currentValue = '' + value;\n      },\n      stopTracking: function () {\n        detachTracker(inst);\n        delete node[valueField];\n      }\n    });\n  },\n\n  updateValueIfChanged: function (inst) {\n    if (!inst) {\n      return false;\n    }\n    var tracker = getTracker(inst);\n\n    if (!tracker) {\n      inputValueTracking.track(inst);\n      return true;\n    }\n\n    var lastValue = tracker.getValue();\n    var nextValue = getValueFromNode(ReactDOMComponentTree.getNodeFromInstance(inst));\n\n    if (nextValue !== lastValue) {\n      tracker.setValue(nextValue);\n      return true;\n    }\n\n    return false;\n  },\n  stopTracking: function (inst) {\n    var tracker = getTracker(inst);\n    if (tracker) {\n      tracker.stopTracking();\n    }\n  }\n};\n\nmodule.exports = inputValueTracking;"},"lineCount":120}},"hash":"ffcd829915cfbb9af021b7f4680df071","cacheData":{"env":{}}}