{"dependencies":[{"name":"/home/kyle/Documents/league-for-good/package.json","includedInParent":true,"mtime":1521424227786},{"name":"/home/kyle/Documents/league-for-good/.babelrc","includedInParent":true,"mtime":1513548591197},{"name":"/home/kyle/Documents/league-for-good/node_modules/lodash-es/package.json","includedInParent":true,"mtime":1513548630089},{"name":"./_ListCache.js","loc":{"line":1,"column":22}},{"name":"./_stackClear.js","loc":{"line":2,"column":23}},{"name":"./_stackDelete.js","loc":{"line":3,"column":24}},{"name":"./_stackGet.js","loc":{"line":4,"column":21}},{"name":"./_stackHas.js","loc":{"line":5,"column":21}},{"name":"./_stackSet.js","loc":{"line":6,"column":21}}],"generated":{"js":"'use strict';\n\nObject.defineProperty(exports, \"__esModule\", {\n  value: true\n});\n\nvar _ListCache = require('./_ListCache.js');\n\nvar _ListCache2 = _interopRequireDefault(_ListCache);\n\nvar _stackClear = require('./_stackClear.js');\n\nvar _stackClear2 = _interopRequireDefault(_stackClear);\n\nvar _stackDelete = require('./_stackDelete.js');\n\nvar _stackDelete2 = _interopRequireDefault(_stackDelete);\n\nvar _stackGet = require('./_stackGet.js');\n\nvar _stackGet2 = _interopRequireDefault(_stackGet);\n\nvar _stackHas = require('./_stackHas.js');\n\nvar _stackHas2 = _interopRequireDefault(_stackHas);\n\nvar _stackSet = require('./_stackSet.js');\n\nvar _stackSet2 = _interopRequireDefault(_stackSet);\n\nfunction _interopRequireDefault(obj) { return obj && obj.__esModule ? obj : { default: obj }; }\n\n/**\n * Creates a stack cache object to store key-value pairs.\n *\n * @private\n * @constructor\n * @param {Array} [entries] The key-value pairs to cache.\n */\nfunction Stack(entries) {\n  var data = this.__data__ = new _ListCache2.default(entries);\n  this.size = data.size;\n}\n\n// Add methods to `Stack`.\nStack.prototype.clear = _stackClear2.default;\nStack.prototype['delete'] = _stackDelete2.default;\nStack.prototype.get = _stackGet2.default;\nStack.prototype.has = _stackHas2.default;\nStack.prototype.set = _stackSet2.default;\n\nexports.default = Stack;","map":{"mappings":[{"generated":{"line":7,"column":0},"source":"../node_modules/lodash-es/_Stack.js","original":{"line":1,"column":0}},{"generated":{"line":11,"column":0},"source":"../node_modules/lodash-es/_Stack.js","original":{"line":2,"column":0}},{"generated":{"line":15,"column":0},"source":"../node_modules/lodash-es/_Stack.js","original":{"line":3,"column":0}},{"generated":{"line":19,"column":0},"source":"../node_modules/lodash-es/_Stack.js","original":{"line":4,"column":0}},{"generated":{"line":23,"column":0},"source":"../node_modules/lodash-es/_Stack.js","original":{"line":5,"column":0}},{"generated":{"line":27,"column":0},"source":"../node_modules/lodash-es/_Stack.js","original":{"line":6,"column":0}},{"generated":{"line":33,"column":0},"source":"../node_modules/lodash-es/_Stack.js","original":{"line":8,"column":0}},{"generated":{"line":40,"column":0},"source":"../node_modules/lodash-es/_Stack.js","original":{"line":15,"column":0}},{"name":"Stack","generated":{"line":40,"column":9},"source":"../node_modules/lodash-es/_Stack.js","original":{"line":15,"column":9}},{"generated":{"line":40,"column":14},"source":"../node_modules/lodash-es/_Stack.js","original":{"line":15,"column":0}},{"name":"entries","generated":{"line":40,"column":15},"source":"../node_modules/lodash-es/_Stack.js","original":{"line":15,"column":15}},{"generated":{"line":40,"column":22},"source":"../node_modules/lodash-es/_Stack.js","original":{"line":15,"column":0}},{"generated":{"line":40,"column":24},"source":"../node_modules/lodash-es/_Stack.js","original":{"line":15,"column":24}},{"generated":{"line":41,"column":0},"source":"../node_modules/lodash-es/_Stack.js","original":{"line":16,"column":2}},{"name":"data","generated":{"line":41,"column":6},"source":"../node_modules/lodash-es/_Stack.js","original":{"line":16,"column":6}},{"generated":{"line":41,"column":13},"source":"../node_modules/lodash-es/_Stack.js","original":{"line":16,"column":13}},{"name":"__data__","generated":{"line":41,"column":18},"source":"../node_modules/lodash-es/_Stack.js","original":{"line":16,"column":18}},{"generated":{"line":41,"column":26},"source":"../node_modules/lodash-es/_Stack.js","original":{"line":16,"column":13}},{"generated":{"line":41,"column":29},"source":"../node_modules/lodash-es/_Stack.js","original":{"line":16,"column":29}},{"name":"entries","generated":{"line":41,"column":53},"source":"../node_modules/lodash-es/_Stack.js","original":{"line":16,"column":43}},{"generated":{"line":41,"column":60},"source":"../node_modules/lodash-es/_Stack.js","original":{"line":16,"column":29}},{"generated":{"line":41,"column":61},"source":"../node_modules/lodash-es/_Stack.js","original":{"line":16,"column":2}},{"generated":{"line":42,"column":0},"source":"../node_modules/lodash-es/_Stack.js","original":{"line":17,"column":2}},{"name":"size","generated":{"line":42,"column":7},"source":"../node_modules/lodash-es/_Stack.js","original":{"line":17,"column":7}},{"generated":{"line":42,"column":11},"source":"../node_modules/lodash-es/_Stack.js","original":{"line":17,"column":2}},{"name":"data","generated":{"line":42,"column":14},"source":"../node_modules/lodash-es/_Stack.js","original":{"line":17,"column":14}},{"name":"size","generated":{"line":42,"column":19},"source":"../node_modules/lodash-es/_Stack.js","original":{"line":17,"column":19}},{"generated":{"line":42,"column":23},"source":"../node_modules/lodash-es/_Stack.js","original":{"line":17,"column":2}},{"generated":{"line":43,"column":0},"source":"../node_modules/lodash-es/_Stack.js","original":{"line":18,"column":1}},{"generated":{"line":45,"column":0},"source":"../node_modules/lodash-es/_Stack.js","original":{"line":20,"column":0}},{"name":"Stack","generated":{"line":46,"column":0},"source":"../node_modules/lodash-es/_Stack.js","original":{"line":21,"column":0}},{"name":"prototype","generated":{"line":46,"column":6},"source":"../node_modules/lodash-es/_Stack.js","original":{"line":21,"column":6}},{"generated":{"line":46,"column":15},"source":"../node_modules/lodash-es/_Stack.js","original":{"line":21,"column":0}},{"name":"clear","generated":{"line":46,"column":16},"source":"../node_modules/lodash-es/_Stack.js","original":{"line":21,"column":16}},{"generated":{"line":46,"column":21},"source":"../node_modules/lodash-es/_Stack.js","original":{"line":21,"column":0}},{"name":"Stack","generated":{"line":47,"column":0},"source":"../node_modules/lodash-es/_Stack.js","original":{"line":22,"column":0}},{"name":"prototype","generated":{"line":47,"column":6},"source":"../node_modules/lodash-es/_Stack.js","original":{"line":22,"column":6}},{"generated":{"line":47,"column":15},"source":"../node_modules/lodash-es/_Stack.js","original":{"line":22,"column":0}},{"generated":{"line":47,"column":16},"source":"../node_modules/lodash-es/_Stack.js","original":{"line":22,"column":16}},{"generated":{"line":47,"column":24},"source":"../node_modules/lodash-es/_Stack.js","original":{"line":22,"column":0}},{"name":"Stack","generated":{"line":48,"column":0},"source":"../node_modules/lodash-es/_Stack.js","original":{"line":23,"column":0}},{"name":"prototype","generated":{"line":48,"column":6},"source":"../node_modules/lodash-es/_Stack.js","original":{"line":23,"column":6}},{"generated":{"line":48,"column":15},"source":"../node_modules/lodash-es/_Stack.js","original":{"line":23,"column":0}},{"name":"get","generated":{"line":48,"column":16},"source":"../node_modules/lodash-es/_Stack.js","original":{"line":23,"column":16}},{"generated":{"line":48,"column":19},"source":"../node_modules/lodash-es/_Stack.js","original":{"line":23,"column":0}},{"name":"Stack","generated":{"line":49,"column":0},"source":"../node_modules/lodash-es/_Stack.js","original":{"line":24,"column":0}},{"name":"prototype","generated":{"line":49,"column":6},"source":"../node_modules/lodash-es/_Stack.js","original":{"line":24,"column":6}},{"generated":{"line":49,"column":15},"source":"../node_modules/lodash-es/_Stack.js","original":{"line":24,"column":0}},{"name":"has","generated":{"line":49,"column":16},"source":"../node_modules/lodash-es/_Stack.js","original":{"line":24,"column":16}},{"generated":{"line":49,"column":19},"source":"../node_modules/lodash-es/_Stack.js","original":{"line":24,"column":0}},{"name":"Stack","generated":{"line":50,"column":0},"source":"../node_modules/lodash-es/_Stack.js","original":{"line":25,"column":0}},{"name":"prototype","generated":{"line":50,"column":6},"source":"../node_modules/lodash-es/_Stack.js","original":{"line":25,"column":6}},{"generated":{"line":50,"column":15},"source":"../node_modules/lodash-es/_Stack.js","original":{"line":25,"column":0}},{"name":"set","generated":{"line":50,"column":16},"source":"../node_modules/lodash-es/_Stack.js","original":{"line":25,"column":16}},{"generated":{"line":50,"column":19},"source":"../node_modules/lodash-es/_Stack.js","original":{"line":25,"column":0}},{"name":"Stack","generated":{"line":52,"column":18},"source":"../node_modules/lodash-es/_Stack.js","original":{"line":27,"column":15}}],"sources":{"../node_modules/lodash-es/_Stack.js":"import ListCache from './_ListCache.js';\nimport stackClear from './_stackClear.js';\nimport stackDelete from './_stackDelete.js';\nimport stackGet from './_stackGet.js';\nimport stackHas from './_stackHas.js';\nimport stackSet from './_stackSet.js';\n\n/**\n * Creates a stack cache object to store key-value pairs.\n *\n * @private\n * @constructor\n * @param {Array} [entries] The key-value pairs to cache.\n */\nfunction Stack(entries) {\n  var data = this.__data__ = new ListCache(entries);\n  this.size = data.size;\n}\n\n// Add methods to `Stack`.\nStack.prototype.clear = stackClear;\nStack.prototype['delete'] = stackDelete;\nStack.prototype.get = stackGet;\nStack.prototype.has = stackHas;\nStack.prototype.set = stackSet;\n\nexport default Stack;\n"},"lineCount":null}},"hash":"7250102ceb1bf062cda02d99861c018b","cacheData":{"env":{}}}