{"dependencies":[{"name":"/home/kyle/Documents/league-for-good/package.json","includedInParent":true,"mtime":1521424227786},{"name":"/home/kyle/Documents/league-for-good/.babelrc","includedInParent":true,"mtime":1513548591197},{"name":"/home/kyle/Documents/league-for-good/node_modules/axios/package.json","includedInParent":true,"mtime":1513548629049},{"name":"./enhanceError","loc":{"line":3,"column":27}}],"generated":{"js":"'use strict';\n\nvar enhanceError = require('./enhanceError');\n\n/**\n * Create an Error with the specified message, config, error code, and response.\n *\n * @param {string} message The error message.\n * @param {Object} config The config.\n * @param {string} [code] The error code (for example, 'ECONNABORTED').\n @ @param {Object} [response] The response.\n * @returns {Error} The created error.\n */\nmodule.exports = function createError(message, config, code, response) {\n  var error = new Error(message);\n  return enhanceError(error, config, code, response);\n};\n","map":{"mappings":[{"source":"../node_modules/axios/lib/core/createError.js","original":{"line":1,"column":0},"generated":{"line":1,"column":0}},{"source":"../node_modules/axios/lib/core/createError.js","original":{"line":2,"column":0},"generated":{"line":2,"column":0}},{"source":"../node_modules/axios/lib/core/createError.js","original":{"line":3,"column":0},"generated":{"line":3,"column":0}},{"source":"../node_modules/axios/lib/core/createError.js","original":{"line":4,"column":0},"generated":{"line":4,"column":0}},{"source":"../node_modules/axios/lib/core/createError.js","original":{"line":5,"column":0},"generated":{"line":5,"column":0}},{"source":"../node_modules/axios/lib/core/createError.js","original":{"line":6,"column":0},"generated":{"line":6,"column":0}},{"source":"../node_modules/axios/lib/core/createError.js","original":{"line":7,"column":0},"generated":{"line":7,"column":0}},{"source":"../node_modules/axios/lib/core/createError.js","original":{"line":8,"column":0},"generated":{"line":8,"column":0}},{"source":"../node_modules/axios/lib/core/createError.js","original":{"line":9,"column":0},"generated":{"line":9,"column":0}},{"source":"../node_modules/axios/lib/core/createError.js","original":{"line":10,"column":0},"generated":{"line":10,"column":0}},{"source":"../node_modules/axios/lib/core/createError.js","original":{"line":11,"column":0},"generated":{"line":11,"column":0}},{"source":"../node_modules/axios/lib/core/createError.js","original":{"line":12,"column":0},"generated":{"line":12,"column":0}},{"source":"../node_modules/axios/lib/core/createError.js","original":{"line":13,"column":0},"generated":{"line":13,"column":0}},{"source":"../node_modules/axios/lib/core/createError.js","original":{"line":14,"column":0},"generated":{"line":14,"column":0}},{"source":"../node_modules/axios/lib/core/createError.js","original":{"line":15,"column":0},"generated":{"line":15,"column":0}},{"source":"../node_modules/axios/lib/core/createError.js","original":{"line":16,"column":0},"generated":{"line":16,"column":0}},{"source":"../node_modules/axios/lib/core/createError.js","original":{"line":17,"column":0},"generated":{"line":17,"column":0}},{"source":"../node_modules/axios/lib/core/createError.js","original":{"line":18,"column":0},"generated":{"line":18,"column":0}}],"sources":{"../node_modules/axios/lib/core/createError.js":"'use strict';\n\nvar enhanceError = require('./enhanceError');\n\n/**\n * Create an Error with the specified message, config, error code, and response.\n *\n * @param {string} message The error message.\n * @param {Object} config The config.\n * @param {string} [code] The error code (for example, 'ECONNABORTED').\n @ @param {Object} [response] The response.\n * @returns {Error} The created error.\n */\nmodule.exports = function createError(message, config, code, response) {\n  var error = new Error(message);\n  return enhanceError(error, config, code, response);\n};\n"},"lineCount":18}},"hash":"1e02bb51759708d85ea29ce7d477a16b","cacheData":{"env":{}}}